ami_helper/__about__.py
ami_helper/__init__.py
ami_helper/__main__.py
ami_helper/ami.py
ami_helper/datamodel.py
ami_helper/disk_cache.py
ami_helper/rucio.py
ami_helper/utils.py
ami_helper-1.0.0b21.dist-info/METADATA
ami_helper-1.0.0b21.dist-info/WHEEL
ami_helper-1.0.0b21.dist-info/entry_points.txt
ami_helper-1.0.0b21.dist-info/licenses/LICENSE.txt
ami_helper-1.0.0b21.dist-info/RECORD
