Metadata-Version: 2.4
Name: ami-helper
Version: 1.0.0b21
Summary: Commansd to help with MCP and data access with AMI in ATLAS
Project-URL: Documentation, https://github.com/Gordon Watts/ami-helper#readme
Project-URL: Issues, https://github.com/Gordon Watts/ami-helper/issues
Project-URL: Source, https://github.com/Gordon Watts/ami-helper
Author-email: Gordon Watts <gwatts@uw.edu>
License-Expression: MIT
License-File: LICENSE.txt
Classifier: Development Status :: 4 - Beta
Classifier: Programming Language :: Python
Classifier: Programming Language :: Python :: 3.8
Classifier: Programming Language :: Python :: 3.9
Classifier: Programming Language :: Python :: 3.10
Classifier: Programming Language :: Python :: 3.11
Classifier: Programming Language :: Python :: Implementation :: CPython
Classifier: Programming Language :: Python :: Implementation :: PyPy
Requires-Python: <3.12,>=3.8
Requires-Dist: diskcache>=5.6.0
Requires-Dist: pyami-core
Requires-Dist: pypika>0.48.8
Requires-Dist: rich>=13.0.0
Requires-Dist: rucio
Requires-Dist: typer>=0.9.0
Provides-Extra: test
Requires-Dist: pytest-cov; extra == 'test'
Requires-Dist: pytest-mock>=3.10.0; extra == 'test'
Requires-Dist: pytest>=7.0.0; extra == 'test'
